yirifi_dq/__init__.py
yirifi_dq/main.py
yirifi_dq/reporting.py
yirifi_dq/commands/__init__.py
yirifi_dq/commands/execute.py
yirifi_dq/commands/list.py
yirifi_dq/commands/logs.py
yirifi_dq/commands/rollback.py
yirifi_dq/commands/run.py
yirifi_dq/commands/scripts.py
yirifi_dq/commands/show.py
yirifi_dq/commands/stats.py
yirifi_dq/commands/verify.py
yirifi_dq/config/__init__.py
yirifi_dq/config/app_config.py
yirifi_dq/config/category_manager.py
yirifi_dq/core/__init__.py
yirifi_dq/core/base_operation.py
yirifi_dq/core/analyzers/__init__.py
yirifi_dq/core/analyzers/fields.py
yirifi_dq/core/analyzers/relationships.py
yirifi_dq/core/analyzers/statistics.py
yirifi_dq/core/backup/__init__.py
yirifi_dq/core/backup/backup.py
yirifi_dq/core/fixers/__init__.py
yirifi_dq/core/fixers/duplicates.py
yirifi_dq/core/fixers/normalizer.py
yirifi_dq/core/fixers/orphans.py
yirifi_dq/core/fixers/pipeline.py
yirifi_dq/core/generators/__init__.py
yirifi_dq/core/generators/slugs.py
yirifi_dq/core/mongodb/__init__.py
yirifi_dq/core/mongodb/mongodb.py
yirifi_dq/core/validators/__init__.py
yirifi_dq/core/validators/consistency.py
yirifi_dq/core/validators/duplicates.py
yirifi_dq/core/validators/orphans.py
yirifi_dq/core/validators/verification.py
yirifi_dq/db/__init__.py
yirifi_dq/db/state_manager.py
yirifi_dq/db/migrations/migrate_schema.py
yirifi_dq/engine/__init__.py
yirifi_dq/engine/orchestrator.py
yirifi_dq/engine/safety.py
yirifi_dq/models/__init__.py
yirifi_dq/models/operation.py
yirifi_dq/models/results.py
yirifi_dq/models/state.py
yirifi_dq/plugins/__init__.py
yirifi_dq/plugins/base_script.py
yirifi_dq/plugins/builtin_wrapper.py
yirifi_dq/plugins/exceptions.py
yirifi_dq/plugins/models.py
yirifi_dq/plugins/orchestrator.py
yirifi_dq/plugins/registry.py
yirifi_dq/scripts/__init__.py
yirifi_dq/scripts/links/__init__.py
yirifi_dq/scripts/links/example_cleanup.py
yirifi_dq/tui/__init__.py
yirifi_dq/tui/app.py
yirifi_dq/tui/wizard.py
yirifi_dq/tui/screens/__init__.py
yirifi_dq-1.0.1.dist-info/METADATA
yirifi_dq-1.0.1.dist-info/WHEEL
yirifi_dq-1.0.1.dist-info/entry_points.txt
yirifi_dq-1.0.1.dist-info/top_level.txt
yirifi_dq-1.0.1.dist-info/RECORD
