Metadata-Version: 2.4
Name: yirifi-dq
Version: 1.0.1
Summary: Terminal-based CLI/TUI for managing MongoDB data quality operations
Author-email: Yirifi Data Team <saurav@yirifi.ai>
License-Expression: LicenseRef-Proprietary
Project-URL: Homepage, https://github.com/yirifi/yirifi-dq
Project-URL: Documentation, https://github.com/yirifi/yirifi-dq#readme
Project-URL: Repository, https://github.com/yirifi/yirifi-dq
Project-URL: Issues, https://github.com/yirifi/yirifi-dq/issues
Keywords: mongodb,data-quality,cli,tui,database,cleanup
Classifier: Development Status :: 4 - Beta
Classifier: Environment :: Console
Classifier: Intended Audience :: Developers
Classifier: Intended Audience :: System Administrators
Classifier: Operating System :: OS Independent
Classifier: Programming Language :: Python :: 3
Classifier: Programming Language :: Python :: 3.8
Classifier: Programming Language :: Python :: 3.9
Classifier: Programming Language :: Python :: 3.10
Classifier: Programming Language :: Python :: 3.11
Classifier: Programming Language :: Python :: 3.12
Classifier: Topic :: Database
Classifier: Topic :: Utilities
Requires-Python: >=3.8
Requires-Dist: click>=8.0.0
Requires-Dist: pymongo>=4.0.0
Requires-Dist: python-dotenv>=1.0.0
Requires-Dist: textual>=0.40.0
Requires-Dist: pydantic>=2.0.0
Requires-Dist: rich>=13.0.0
Requires-Dist: pyyaml>=6.0
Requires-Dist: tabulate>=0.9.0
Provides-Extra: dev
Requires-Dist: pytest>=7.0.0; extra == "dev"
Requires-Dist: pytest-cov>=4.0.0; extra == "dev"
Requires-Dist: black>=23.0.0; extra == "dev"
Requires-Dist: ruff>=0.1.0; extra == "dev"
Requires-Dist: mypy>=1.0.0; extra == "dev"
Requires-Dist: bandit>=1.7.0; extra == "dev"
